suit_ckeditor/__init__.py
suit_ckeditor/models.py
suit_ckeditor/widgets.py
suit_ckeditor/static/suit-ckeditor/ckeditor.css
suit_ckeditor/static/suit-ckeditor/ckeditor/CHANGES.md
suit_ckeditor/static/suit-ckeditor/ckeditor/LICENSE.md
suit_ckeditor/static/suit-ckeditor/ckeditor/README.md
suit_ckeditor/static/suit-ckeditor/ckeditor/bender-runner.config.json
suit_ckeditor/static/suit-ckeditor/ckeditor/build-config.js
suit_ckeditor/static/suit-ckeditor/ckeditor/ckeditor.js
suit_ckeditor/static/suit-ckeditor/ckeditor/config.js
suit_ckeditor/static/suit-ckeditor/ckeditor/contents.css
suit_ckeditor/static/suit-ckeditor/ckeditor/styles.js
suit_ckeditor/static/suit-ckeditor/ckeditor/adapters/jquery.js
suit_ckeditor/static/suit-ckeditor/ckeditor/lang/af.js
suit_ckeditor/static/suit-ckeditor/ckeditor/lang/ar.js
suit_ckeditor/static/suit-ckeditor/ckeditor/lang/az.js
suit_ckeditor/static/suit-ckeditor/ckeditor/lang/bg.js
suit_ckeditor/static/suit-ckeditor/ckeditor/lang/bn.js
suit_ckeditor/static/suit-ckeditor/ckeditor/lang/bs.js
suit_ckeditor/static/suit-ckeditor/ckeditor/lang/ca.js
suit_ckeditor/static/suit-ckeditor/ckeditor/lang/cs.js
suit_ckeditor/static/suit-ckeditor/ckeditor/lang/cy.js
suit_ckeditor/static/suit-ckeditor/ckeditor/lang/da.js
suit_ckeditor/static/suit-ckeditor/ckeditor/lang/de-ch.js
suit_ckeditor/static/suit-ckeditor/ckeditor/lang/de.js
suit_ckeditor/static/suit-ckeditor/ckeditor/lang/el.js
suit_ckeditor/static/suit-ckeditor/ckeditor/lang/en-au.js
suit_ckeditor/static/suit-ckeditor/ckeditor/lang/en-ca.js
suit_ckeditor/static/suit-ckeditor/ckeditor/lang/en-gb.js
suit_ckeditor/static/suit-ckeditor/ckeditor/lang/en.js
suit_ckeditor/static/suit-ckeditor/ckeditor/lang/eo.js
suit_ckeditor/static/suit-ckeditor/ckeditor/lang/es-mx.js
suit_ckeditor/static/suit-ckeditor/ckeditor/lang/es.js
suit_ckeditor/static/suit-ckeditor/ckeditor/lang/et.js
suit_ckeditor/static/suit-ckeditor/ckeditor/lang/eu.js
suit_ckeditor/static/suit-ckeditor/ckeditor/lang/fa.js
django_suit_ckeditor_custom-1.0.11.dist-info/METADATA
django_suit_ckeditor_custom-1.0.11.dist-info/WHEEL
django_suit_ckeditor_custom-1.0.11.dist-info/top_level.txt
django_suit_ckeditor_custom-1.0.11.dist-info/RECORD
