Metadata-Version: 2.1
Name: django-suit-ckeditor-custom
Version: 1.0.11
Summary: CKEditor (WYSIWYG editor) integration app for Django admin. http://ckeditor.com
Home-page: https://github.com/darklow/django-suit-ckeditor
Author: Kaspars Sprogis (darklow)
Author-email: info@djangosuit.com
License: UNKNOWN
Platform: UNKNOWN
Classifier: Development Status :: 5 - Production/Stable
Classifier: Framework :: Django
Classifier: License :: OSI Approved
Classifier: Intended Audience :: Developers
Classifier: Intended Audience :: System Administrators
Classifier: Programming Language :: Python
Classifier: Environment :: Web Environment
Classifier: Topic :: Software Development :: User Interfaces
